pantam/__init__.py
pantam/pantam.py
pantam/services/__init__.py
pantam/services/logger.py
pantam_cli/__init__.py
pantam_cli/action.py
pantam_cli/cli.py
pantam_cli/init.py
pantam_cli/serve.py
pantam_cli/utils/__init__.py
pantam_cli/utils/errors.py
pantam_cli/utils/filesystem.py
pantam_cli/utils/messages.py
pantam_cli/utils/templates.py
pantam-1.0.4.dist-info/entry_points.txt
pantam-1.0.4.dist-info/LICENSE.md
pantam-1.0.4.dist-info/WHEEL
pantam-1.0.4.dist-info/METADATA
pantam-1.0.4.dist-info/RECORD
