Metadata-Version: 2.1
Name: pantam
Version: 1.0.4
Summary: The microframework for microservices
Home-page: https://github.com/flmnt/pantam/blob/master/README.md
License: MIT
Author: Matt Davies
Author-email: matt@filament.so
Requires-Python: >=3.6.1,<4.0.0
Classifier: License :: OSI Approved :: MIT License
Classifier: Programming Language :: Python :: 3
Classifier: Programming Language :: Python :: 3.7
Classifier: Programming Language :: Python :: 3.8
Classifier: Programming Language :: Python :: 3.9
Requires-Dist: colored (>=1.4.2,<2.0.0)
Requires-Dist: prompt_toolkit (>=3.0.5,<4.0.0)
Requires-Dist: python-multipart (>=0.0.5,<0.0.6)
Requires-Dist: shellingham (>=1.3.2,<2.0.0)
Requires-Dist: starlette (>=0.13.6,<0.14.0)
Requires-Dist: typer (>=0.3.1,<0.4.0)
Requires-Dist: uvicorn (>=0.11.6,<0.12.0)
Project-URL: Repository, https://github.com/flmnt/pantam
